namedframes/__init__.py
namedframes/namedframes.py
namedframes/pandas_frames.py
namedframes/spark_frames.py
namedframes-0.1.4.dist-info/LICENSE
namedframes-0.1.4.dist-info/METADATA
namedframes-0.1.4.dist-info/WHEEL
namedframes-0.1.4.dist-info/top_level.txt
namedframes-0.1.4.dist-info/RECORD
