Metadata-Version: 2.1
Name: namedframes
Version: 0.1.4
Summary: Named Data Frames
Home-page: https://github.com/bdilday/namedframes
Author: Ben Dilday
Author-email: ben.dilday.phd@gmail.com
License: MIT license
Keywords: namedframes
Platform: UNKNOWN
Classifier: Development Status :: 2 - Pre-Alpha
Classifier: Intended Audience :: Developers
Classifier: License :: OSI Approved :: MIT License
Classifier: Natural Language :: English
Classifier: Programming Language :: Python :: 3
Classifier: Programming Language :: Python :: 3.6
Classifier: Programming Language :: Python :: 3.7
Classifier: Programming Language :: Python :: 3.8
Requires-Python: >=3.6
Provides-Extra: pyspark
Requires-Dist: pyspark (>=2.4.5) ; extra == 'pyspark'
